{
  "project": "corvus",
  "version": "v1",
  "statement": "OBD-II telemetry ingestion, SQL analytics, and drive health scoring.",
  "focus": {
    "session_id": 5,
    "vehicle": "VED Car 1.5L",
    "source": "public",
    "notes": "Vehicle Energy Dataset (VED) real OBD-II entry; source_file=VED_171101_week.csv; trip_ref=VehId=8; Trip=708; drive_label=Ann Arbor week log; license=Apache-2.0.",
    "source_file": "VED_171101_week.csv",
    "drive_label": "Ann Arbor week log",
    "started_at": "2017-11-02T13:51:53.106Z",
    "ended_at": "2017-11-02T13:55:03.506Z",
    "health_score": "95.0",
    "health_score_width": "95.0%",
    "metric_penalty_points": "4.9",
    "dtc_penalty_points": "0.0",
    "dtc_count": "0",
    "telemetry_samples": "240",
    "score_basis": "directional editable scoring config",
    "pct_out_of_range": "0.0",
    "baseline_width": "0.0%",
    "out_of_range_samples": "0",
    "sample_count": "0"
  },
  "defaultSessionId": 5,
  "sessionViews": {
    "3": {
      "focus": {
        "session_id": 3,
        "vehicle": "Seat Leon",
        "source": "public",
        "notes": "KIT/RADAR Automotive OBD-II Dataset real OBD-II entry; source_file=2018-03-26_Seat_Leon_S_RT_Stau.csv; drive_label=Traffic jam log; license=CC BY 4.0.",
        "source_file": "2018-03-26_Seat_Leon_S_RT_Stau.csv",
        "drive_label": "Traffic jam log",
        "started_at": "2018-03-26T18:06:33.719Z",
        "ended_at": "2018-03-26T18:10:32.038Z",
        "health_score": "100.0",
        "health_score_width": "100.0%",
        "metric_penalty_points": "0.0",
        "dtc_penalty_points": "0.0",
        "dtc_count": "0",
        "telemetry_samples": "240",
        "score_basis": "directional editable scoring config",
        "pct_out_of_range": "0.0",
        "baseline_width": "0.0%",
        "out_of_range_samples": "0",
        "sample_count": "240"
      },
      "trend": [
        {
          "ts": "2018-03-26T18:06:33.719Z",
          "maf_gps": "7.13",
          "maf_30s": "7.13",
          "height_pct": "41.1%"
        },
        {
          "ts": "2018-03-26T18:06:43.050Z",
          "maf_gps": "13.66",
          "maf_30s": "10.00",
          "height_pct": "52.0%"
        },
        {
          "ts": "2018-03-26T18:06:53.069Z",
          "maf_gps": "7.80",
          "maf_30s": "11.82",
          "height_pct": "58.9%"
        },
        {
          "ts": "2018-03-26T18:07:03.029Z",
          "maf_gps": "7.47",
          "maf_30s": "10.64",
          "height_pct": "54.4%"
        },
        {
          "ts": "2018-03-26T18:07:13.049Z",
          "maf_gps": "7.97",
          "maf_30s": "10.82",
          "height_pct": "55.1%"
        },
        {
          "ts": "2018-03-26T18:07:23.069Z",
          "maf_gps": "10.38",
          "maf_30s": "9.38",
          "height_pct": "49.6%"
        },
        {
          "ts": "2018-03-26T18:07:33.059Z",
          "maf_gps": "7.97",
          "maf_30s": "9.95",
          "height_pct": "51.8%"
        },
        {
          "ts": "2018-03-26T18:07:43.019Z",
          "maf_gps": "17.91",
          "maf_30s": "10.19",
          "height_pct": "52.7%"
        },
        {
          "ts": "2018-03-26T18:07:53.008Z",
          "maf_gps": "11.38",
          "maf_30s": "13.36",
          "height_pct": "64.7%"
        },
        {
          "ts": "2018-03-26T18:08:03.060Z",
          "maf_gps": "20.36",
          "maf_30s": "16.93",
          "height_pct": "78.3%"
        },
        {
          "ts": "2018-03-26T18:08:13.079Z",
          "maf_gps": "23.77",
          "maf_30s": "18.43",
          "height_pct": "84.0%"
        },
        {
          "ts": "2018-03-26T18:08:23.008Z",
          "maf_gps": "8.88",
          "maf_30s": "16.38",
          "height_pct": "76.2%"
        },
        {
          "ts": "2018-03-26T18:08:33.028Z",
          "maf_gps": "13.66",
          "maf_30s": "14.32",
          "height_pct": "68.4%"
        },
        {
          "ts": "2018-03-26T18:08:43.078Z",
          "maf_gps": "11.02",
          "maf_30s": "14.02",
          "height_pct": "67.3%"
        },
        {
          "ts": "2018-03-26T18:08:53.038Z",
          "maf_gps": "8.97",
          "maf_30s": "13.30",
          "height_pct": "64.5%"
        },
        {
          "ts": "2018-03-26T18:09:03.058Z",
          "maf_gps": "14.05",
          "maf_30s": "13.91",
          "height_pct": "66.8%"
        },
        {
          "ts": "2018-03-26T18:09:13.078Z",
          "maf_gps": "22.05",
          "maf_30s": "14.59",
          "height_pct": "69.4%"
        },
        {
          "ts": "2018-03-26T18:09:23.069Z",
          "maf_gps": "10.77",
          "maf_30s": "14.85",
          "height_pct": "70.4%"
        },
        {
          "ts": "2018-03-26T18:09:33.088Z",
          "maf_gps": "22.27",
          "maf_30s": "14.77",
          "height_pct": "70.1%"
        },
        {
          "ts": "2018-03-26T18:09:43.018Z",
          "maf_gps": "10.22",
          "maf_30s": "15.50",
          "height_pct": "72.9%"
        },
        {
          "ts": "2018-03-26T18:09:53.069Z",
          "maf_gps": "16.24",
          "maf_30s": "16.77",
          "height_pct": "77.7%"
        },
        {
          "ts": "2018-03-26T18:10:03.028Z",
          "maf_gps": "22.52",
          "maf_30s": "17.44",
          "height_pct": "80.2%"
        },
        {
          "ts": "2018-03-26T18:10:13.078Z",
          "maf_gps": "10.83",
          "maf_30s": "15.55",
          "height_pct": "73.1%"
        },
        {
          "ts": "2018-03-26T18:10:23.069Z",
          "maf_gps": "10.36",
          "maf_30s": "12.80",
          "height_pct": "62.6%"
        },
        {
          "ts": "2018-03-26T18:10:32.038Z",
          "maf_gps": "15.72",
          "maf_30s": "12.27",
          "height_pct": "60.6%"
        }
      ],
      "dtcEvidence": [
        {
          "code": "none logged",
          "status": "none",
          "description": "No diagnostic trouble code was logged in this real public entry.",
          "fault_ts": "",
          "ts": "",
          "rpm": "n/a",
          "engine_load_pct": "n/a",
          "coolant_temp_c": "n/a"
        }
      ],
      "healthMatrix": [
        {
          "id": "drive_health",
          "label": "Drive health",
          "value": "100.0",
          "width_pct": "100.0%"
        },
        {
          "id": "baseline_fit",
          "label": "Baseline fit",
          "value": "100.0",
          "width_pct": "100.0%"
        },
        {
          "id": "airflow",
          "label": "Airflow",
          "value": "47.9",
          "width_pct": "47.9%"
        },
        {
          "id": "fault_clearance",
          "label": "Fault clearance",
          "value": "100.0",
          "width_pct": "100.0%"
        },
        {
          "id": "sensor_balance",
          "label": "Sensor balance",
          "value": "100.0",
          "width_pct": "100.0%"
        }
      ],
      "performanceConcerns": [
        {
          "level": "watch",
          "text": "Mass airflow moved up and down sharply across the drive \u2014 that can mean unstable idle, a boost event, or a noisy MAF signal."
        }
      ],
      "agentTrace": [
        {
          "agent": "corvus",
          "node": "agent_trace",
          "kind": "deterministic",
          "summary": "Trace created before analysis output.",
          "title": "Open trace",
          "body": "Trace created before analysis output.",
          "agent_name": "Corvus",
          "agent_tagline": "Writes the report"
        },
        {
          "agent": "huginn",
          "node": "ingest_normalizer",
          "kind": "deterministic",
          "summary": "Loaded the logged drive from the database.",
          "title": "Load the drive",
          "body": "Loaded the logged drive from the database.",
          "agent_name": "Huginn",
          "agent_tagline": "Reads this drive"
        },
        {
          "agent": "huginn",
          "node": "sql_deviation",
          "kind": "deterministic",
          "summary": "Ran SQL health score, baseline drift, trim trend, and fault-window queries.",
          "title": "Run SQL checks",
          "body": "Ran SQL health score, baseline drift, trim trend, and fault-window queries.",
          "agent_name": "Huginn",
          "agent_tagline": "Reads this drive"
        },
        {
          "agent": "huginn",
          "node": "dtc_interpreter",
          "kind": "deterministic",
          "summary": "Listed diagnostic trouble codes logged on this drive.",
          "title": "Read fault codes",
          "body": "Listed diagnostic trouble codes logged on this drive.",
          "agent_name": "Huginn",
          "agent_tagline": "Reads this drive"
        },
        {
          "agent": "muninn",
          "node": "baseline_recall",
          "kind": "deterministic",
          "summary": "Loaded stored healthy ranges for this vehicle.",
          "title": "Load healthy ranges",
          "body": "Loaded stored healthy ranges for this vehicle.",
          "agent_name": "Muninn",
          "agent_tagline": "Recalls what normal looks like"
        },
        {
          "agent": "muninn",
          "node": "correlation",
          "kind": "deterministic",
          "summary": "Matched fault timestamps to nearby engine sensor rows.",
          "title": "Match faults to sensors",
          "body": "Matched fault timestamps to nearby engine sensor rows.",
          "agent_name": "Muninn",
          "agent_tagline": "Recalls what normal looks like"
        },
        {
          "agent": "muninn",
          "node": "recommendation",
          "kind": "deterministic",
          "summary": "Ranked what to inspect next from SQL facts only.",
          "title": "State next checks",
          "body": "Ranked what to inspect next from SQL facts only.",
          "agent_name": "Muninn",
          "agent_tagline": "Recalls what normal looks like"
        },
        {
          "agent": "corvus",
          "node": "report_writer",
          "kind": "deterministic",
          "summary": "Saved the finding with trace id for audit.",
          "title": "Save finding",
          "body": "Saved the finding with trace id for audit.",
          "agent_name": "Corvus",
          "agent_tagline": "Writes the report"
        }
      ],
      "agentTraceId": "agent-bb768ca247e840cdbbddce323f42df8b",
      "dtcSummary": "No DTC rows were logged for this session."
    },
    "4": {
      "focus": {
        "session_id": 4,
        "vehicle": "VED ICE 6.0L V8",
        "source": "public",
        "notes": "Vehicle Energy Dataset (VED) real OBD-II entry; source_file=VED_171101_week.csv; trip_ref=VehId=108; Trip=784; drive_label=Ann Arbor week log; license=Apache-2.0.",
        "source_file": "VED_171101_week.csv",
        "drive_label": "Ann Arbor week log",
        "started_at": "2017-11-02T13:27:31.820Z",
        "ended_at": "2017-11-02T13:30:47.520Z",
        "health_score": "96.2",
        "health_score_width": "96.2%",
        "metric_penalty_points": "3.9",
        "dtc_penalty_points": "0.0",
        "dtc_count": "0",
        "telemetry_samples": "240",
        "score_basis": "directional editable scoring config",
        "pct_out_of_range": "0.0",
        "baseline_width": "0.0%",
        "out_of_range_samples": "0",
        "sample_count": "0"
      },
      "trend": [
        {
          "ts": "2017-11-02T13:27:31.820Z",
          "maf_gps": "9.83",
          "maf_30s": "9.83",
          "height_pct": "45.8%"
        },
        {
          "ts": "2017-11-02T13:27:41.220Z",
          "maf_gps": "8.14",
          "maf_30s": "8.72",
          "height_pct": "42.2%"
        },
        {
          "ts": "2017-11-02T13:27:51.520Z",
          "maf_gps": "8.97",
          "maf_30s": "8.20",
          "height_pct": "40.5%"
        },
        {
          "ts": "2017-11-02T13:27:59.720Z",
          "maf_gps": "6.46",
          "maf_30s": "7.98",
          "height_pct": "39.8%"
        },
        {
          "ts": "2017-11-02T13:28:17.120Z",
          "maf_gps": "5.92",
          "maf_30s": "7.08",
          "height_pct": "36.9%"
        },
        {
          "ts": "2017-11-02T13:28:27.820Z",
          "maf_gps": "31.92",
          "maf_30s": "7.72",
          "height_pct": "39.0%"
        },
        {
          "ts": "2017-11-02T13:28:33.820Z",
          "maf_gps": "28.30",
          "maf_30s": "17.35",
          "height_pct": "70.2%"
        },
        {
          "ts": "2017-11-02T13:28:44.320Z",
          "maf_gps": "8.06",
          "maf_30s": "19.82",
          "height_pct": "78.2%"
        },
        {
          "ts": "2017-11-02T13:28:56.820Z",
          "maf_gps": "7.88",
          "maf_30s": "21.62",
          "height_pct": "84.0%"
        },
        {
          "ts": "2017-11-02T13:29:06.220Z",
          "maf_gps": "29.93",
          "maf_30s": "15.32",
          "height_pct": "63.6%"
        },
        {
          "ts": "2017-11-02T13:29:15.320Z",
          "maf_gps": "19.05",
          "maf_30s": "17.41",
          "height_pct": "70.4%"
        },
        {
          "ts": "2017-11-02T13:29:26.720Z",
          "maf_gps": "10.28",
          "maf_30s": "16.46",
          "height_pct": "67.3%"
        },
        {
          "ts": "2017-11-02T13:29:31.820Z",
          "maf_gps": "26.47",
          "maf_30s": "15.36",
          "height_pct": "63.7%"
        },
        {
          "ts": "2017-11-02T13:29:36.720Z",
          "maf_gps": "47.86",
          "maf_30s": "19.08",
          "height_pct": "75.8%"
        },
        {
          "ts": "2017-11-02T13:29:45.020Z",
          "maf_gps": "9.35",
          "maf_30s": "20.81",
          "height_pct": "81.4%"
        },
        {
          "ts": "2017-11-02T13:29:49.120Z",
          "maf_gps": "10.58",
          "maf_30s": "20.14",
          "height_pct": "79.2%"
        },
        {
          "ts": "2017-11-02T13:29:54.120Z",
          "maf_gps": "7.14",
          "maf_30s": "12.62",
          "height_pct": "54.9%"
        },
        {
          "ts": "2017-11-02T13:30:01.320Z",
          "maf_gps": "10.61",
          "maf_30s": "9.46",
          "height_pct": "44.6%"
        },
        {
          "ts": "2017-11-02T13:30:06.320Z",
          "maf_gps": "44.86",
          "maf_30s": "11.85",
          "height_pct": "52.4%"
        },
        {
          "ts": "2017-11-02T13:30:15.520Z",
          "maf_gps": "12.10",
          "maf_30s": "15.21",
          "height_pct": "63.2%"
        },
        {
          "ts": "2017-11-02T13:30:27.920Z",
          "maf_gps": "7.97",
          "maf_30s": "15.22",
          "height_pct": "63.3%"
        },
        {
          "ts": "2017-11-02T13:30:34.020Z",
          "maf_gps": "6.10",
          "maf_30s": "13.17",
          "height_pct": "56.6%"
        },
        {
          "ts": "2017-11-02T13:30:38.920Z",
          "maf_gps": "9.35",
          "maf_30s": "11.73",
          "height_pct": "52.0%"
        },
        {
          "ts": "2017-11-02T13:30:42.020Z",
          "maf_gps": "7.59",
          "maf_30s": "11.29",
          "height_pct": "50.6%"
        },
        {
          "ts": "2017-11-02T13:30:47.520Z",
          "maf_gps": "20.28",
          "maf_30s": "13.10",
          "height_pct": "56.4%"
        }
      ],
      "dtcEvidence": [
        {
          "code": "none logged",
          "status": "none",
          "description": "No diagnostic trouble code was logged in this real public entry.",
          "fault_ts": "",
          "ts": "",
          "rpm": "n/a",
          "engine_load_pct": "n/a",
          "coolant_temp_c": "n/a"
        }
      ],
      "healthMatrix": [
        {
          "id": "drive_health",
          "label": "Drive health",
          "value": "96.2",
          "width_pct": "96.2%"
        },
        {
          "id": "baseline_fit",
          "label": "Baseline fit",
          "value": "100.0",
          "width_pct": "100.0%"
        },
        {
          "id": "airflow",
          "label": "Airflow",
          "value": "42.8",
          "width_pct": "42.8%"
        },
        {
          "id": "fault_clearance",
          "label": "Fault clearance",
          "value": "100.0",
          "width_pct": "100.0%"
        },
        {
          "id": "sensor_balance",
          "label": "Sensor balance",
          "value": "84.4",
          "width_pct": "84.4%"
        }
      ],
      "performanceConcerns": [
        {
          "level": "watch",
          "text": "Mass airflow moved up and down sharply across the drive \u2014 that can mean unstable idle, a boost event, or a noisy MAF signal."
        }
      ],
      "agentTrace": [
        {
          "agent": "corvus",
          "node": "agent_trace",
          "kind": "deterministic",
          "summary": "Trace created before analysis output.",
          "title": "Open trace",
          "body": "Trace created before analysis output.",
          "agent_name": "Corvus",
          "agent_tagline": "Writes the report"
        },
        {
          "agent": "huginn",
          "node": "ingest_normalizer",
          "kind": "deterministic",
          "summary": "Loaded the logged drive from the database.",
          "title": "Load the drive",
          "body": "Loaded the logged drive from the database.",
          "agent_name": "Huginn",
          "agent_tagline": "Reads this drive"
        },
        {
          "agent": "huginn",
          "node": "sql_deviation",
          "kind": "deterministic",
          "summary": "Ran SQL health score, baseline drift, trim trend, and fault-window queries.",
          "title": "Run SQL checks",
          "body": "Ran SQL health score, baseline drift, trim trend, and fault-window queries.",
          "agent_name": "Huginn",
          "agent_tagline": "Reads this drive"
        },
        {
          "agent": "huginn",
          "node": "dtc_interpreter",
          "kind": "deterministic",
          "summary": "Listed diagnostic trouble codes logged on this drive.",
          "title": "Read fault codes",
          "body": "Listed diagnostic trouble codes logged on this drive.",
          "agent_name": "Huginn",
          "agent_tagline": "Reads this drive"
        },
        {
          "agent": "muninn",
          "node": "baseline_recall",
          "kind": "deterministic",
          "summary": "Loaded stored healthy ranges for this vehicle.",
          "title": "Load healthy ranges",
          "body": "Loaded stored healthy ranges for this vehicle.",
          "agent_name": "Muninn",
          "agent_tagline": "Recalls what normal looks like"
        },
        {
          "agent": "muninn",
          "node": "correlation",
          "kind": "deterministic",
          "summary": "Matched fault timestamps to nearby engine sensor rows.",
          "title": "Match faults to sensors",
          "body": "Matched fault timestamps to nearby engine sensor rows.",
          "agent_name": "Muninn",
          "agent_tagline": "Recalls what normal looks like"
        },
        {
          "agent": "muninn",
          "node": "recommendation",
          "kind": "deterministic",
          "summary": "Ranked what to inspect next from SQL facts only.",
          "title": "State next checks",
          "body": "Ranked what to inspect next from SQL facts only.",
          "agent_name": "Muninn",
          "agent_tagline": "Recalls what normal looks like"
        },
        {
          "agent": "corvus",
          "node": "report_writer",
          "kind": "deterministic",
          "summary": "Saved the finding with trace id for audit.",
          "title": "Save finding",
          "body": "Saved the finding with trace id for audit.",
          "agent_name": "Corvus",
          "agent_tagline": "Writes the report"
        }
      ],
      "agentTraceId": "agent-8b9cb978172b420b91a5f289e8ff1351",
      "dtcSummary": "No DTC rows were logged for this session."
    },
    "5": {
      "focus": {
        "session_id": 5,
        "vehicle": "VED Car 1.5L",
        "source": "public",
        "notes": "Vehicle Energy Dataset (VED) real OBD-II entry; source_file=VED_171101_week.csv; trip_ref=VehId=8; Trip=708; drive_label=Ann Arbor week log; license=Apache-2.0.",
        "source_file": "VED_171101_week.csv",
        "drive_label": "Ann Arbor week log",
        "started_at": "2017-11-02T13:51:53.106Z",
        "ended_at": "2017-11-02T13:55:03.506Z",
        "health_score": "95.0",
        "health_score_width": "95.0%",
        "metric_penalty_points": "4.9",
        "dtc_penalty_points": "0.0",
        "dtc_count": "0",
        "telemetry_samples": "240",
        "score_basis": "directional editable scoring config",
        "pct_out_of_range": "0.0",
        "baseline_width": "0.0%",
        "out_of_range_samples": "0",
        "sample_count": "0"
      },
      "trend": [
        {
          "ts": "2017-11-02T13:51:53.106Z",
          "maf_gps": "6.70",
          "maf_30s": "6.70",
          "height_pct": "43.4%"
        },
        {
          "ts": "2017-11-02T13:51:58.906Z",
          "maf_gps": "15.60",
          "maf_30s": "12.36",
          "height_pct": "68.2%"
        },
        {
          "ts": "2017-11-02T13:52:06.606Z",
          "maf_gps": "4.48",
          "maf_30s": "9.86",
          "height_pct": "57.3%"
        },
        {
          "ts": "2017-11-02T13:52:12.806Z",
          "maf_gps": "9.54",
          "maf_30s": "8.63",
          "height_pct": "51.9%"
        },
        {
          "ts": "2017-11-02T13:52:19.306Z",
          "maf_gps": "15.69",
          "maf_30s": "9.55",
          "height_pct": "55.9%"
        },
        {
          "ts": "2017-11-02T13:52:26.706Z",
          "maf_gps": "6.91",
          "maf_30s": "9.80",
          "height_pct": "57.0%"
        },
        {
          "ts": "2017-11-02T13:52:36.206Z",
          "maf_gps": "18.97",
          "maf_30s": "12.01",
          "height_pct": "66.7%"
        },
        {
          "ts": "2017-11-02T13:52:43.506Z",
          "maf_gps": "6.15",
          "maf_30s": "11.14",
          "height_pct": "62.9%"
        },
        {
          "ts": "2017-11-02T13:52:53.806Z",
          "maf_gps": "2.93",
          "maf_30s": "9.18",
          "height_pct": "54.3%"
        },
        {
          "ts": "2017-11-02T13:53:03.306Z",
          "maf_gps": "2.96",
          "maf_30s": "6.52",
          "height_pct": "42.6%"
        },
        {
          "ts": "2017-11-02T13:53:13.806Z",
          "maf_gps": "3.55",
          "maf_30s": "3.48",
          "height_pct": "29.3%"
        },
        {
          "ts": "2017-11-02T13:53:19.106Z",
          "maf_gps": "3.52",
          "maf_30s": "3.31",
          "height_pct": "28.5%"
        },
        {
          "ts": "2017-11-02T13:53:24.806Z",
          "maf_gps": "16.65",
          "maf_30s": "3.90",
          "height_pct": "31.1%"
        },
        {
          "ts": "2017-11-02T13:53:30.706Z",
          "maf_gps": "21.33",
          "maf_30s": "8.19",
          "height_pct": "49.9%"
        },
        {
          "ts": "2017-11-02T13:53:37.906Z",
          "maf_gps": "22.01",
          "maf_30s": "12.26",
          "height_pct": "67.8%"
        },
        {
          "ts": "2017-11-02T13:53:48.606Z",
          "maf_gps": "3.64",
          "maf_30s": "15.31",
          "height_pct": "81.2%"
        },
        {
          "ts": "2017-11-02T13:53:59.006Z",
          "maf_gps": "2.93",
          "maf_30s": "11.13",
          "height_pct": "62.8%"
        },
        {
          "ts": "2017-11-02T13:54:09.406Z",
          "maf_gps": "21.90",
          "maf_30s": "11.17",
          "height_pct": "63.0%"
        },
        {
          "ts": "2017-11-02T13:54:19.206Z",
          "maf_gps": "23.93",
          "maf_30s": "14.85",
          "height_pct": "79.2%"
        },
        {
          "ts": "2017-11-02T13:54:25.706Z",
          "maf_gps": "5.69",
          "maf_30s": "15.95",
          "height_pct": "84.0%"
        },
        {
          "ts": "2017-11-02T13:54:34.106Z",
          "maf_gps": "3.58",
          "maf_30s": "12.95",
          "height_pct": "70.8%"
        },
        {
          "ts": "2017-11-02T13:54:43.406Z",
          "maf_gps": "3.67",
          "maf_30s": "5.73",
          "height_pct": "39.1%"
        },
        {
          "ts": "2017-11-02T13:54:50.706Z",
          "maf_gps": "2.58",
          "maf_30s": "4.14",
          "height_pct": "32.2%"
        },
        {
          "ts": "2017-11-02T13:54:58.006Z",
          "maf_gps": "23.54",
          "maf_30s": "5.46",
          "height_pct": "38.0%"
        },
        {
          "ts": "2017-11-02T13:55:03.506Z",
          "maf_gps": "23.80",
          "maf_30s": "11.88",
          "height_pct": "66.1%"
        }
      ],
      "dtcEvidence": [
        {
          "code": "none logged",
          "status": "none",
          "description": "No diagnostic trouble code was logged in this real public entry.",
          "fault_ts": "",
          "ts": "",
          "rpm": "n/a",
          "engine_load_pct": "n/a",
          "coolant_temp_c": "n/a"
        }
      ],
      "healthMatrix": [
        {
          "id": "drive_health",
          "label": "Drive health",
          "value": "95.0",
          "width_pct": "95.0%"
        },
        {
          "id": "baseline_fit",
          "label": "Baseline fit",
          "value": "100.0",
          "width_pct": "100.0%"
        },
        {
          "id": "airflow",
          "label": "Airflow",
          "value": "32.6",
          "width_pct": "32.6%"
        },
        {
          "id": "fault_clearance",
          "label": "Fault clearance",
          "value": "100.0",
          "width_pct": "100.0%"
        },
        {
          "id": "sensor_balance",
          "label": "Sensor balance",
          "value": "80.4",
          "width_pct": "80.4%"
        }
      ],
      "performanceConcerns": [
        {
          "level": "watch",
          "text": "Mass airflow moved up and down sharply across the drive \u2014 that can mean unstable idle, a boost event, or a noisy MAF signal."
        }
      ],
      "agentTrace": [
        {
          "agent": "corvus",
          "node": "agent_trace",
          "kind": "deterministic",
          "summary": "Trace created before analysis output.",
          "title": "Open trace",
          "body": "Trace created before analysis output.",
          "agent_name": "Corvus",
          "agent_tagline": "Writes the report"
        },
        {
          "agent": "huginn",
          "node": "ingest_normalizer",
          "kind": "deterministic",
          "summary": "Loaded the logged drive from the database.",
          "title": "Load the drive",
          "body": "Loaded the logged drive from the database.",
          "agent_name": "Huginn",
          "agent_tagline": "Reads this drive"
        },
        {
          "agent": "huginn",
          "node": "sql_deviation",
          "kind": "deterministic",
          "summary": "Ran SQL health score, baseline drift, trim trend, and fault-window queries.",
          "title": "Run SQL checks",
          "body": "Ran SQL health score, baseline drift, trim trend, and fault-window queries.",
          "agent_name": "Huginn",
          "agent_tagline": "Reads this drive"
        },
        {
          "agent": "huginn",
          "node": "dtc_interpreter",
          "kind": "deterministic",
          "summary": "Listed diagnostic trouble codes logged on this drive.",
          "title": "Read fault codes",
          "body": "Listed diagnostic trouble codes logged on this drive.",
          "agent_name": "Huginn",
          "agent_tagline": "Reads this drive"
        },
        {
          "agent": "muninn",
          "node": "baseline_recall",
          "kind": "deterministic",
          "summary": "Loaded stored healthy ranges for this vehicle.",
          "title": "Load healthy ranges",
          "body": "Loaded stored healthy ranges for this vehicle.",
          "agent_name": "Muninn",
          "agent_tagline": "Recalls what normal looks like"
        },
        {
          "agent": "muninn",
          "node": "correlation",
          "kind": "deterministic",
          "summary": "Matched fault timestamps to nearby engine sensor rows.",
          "title": "Match faults to sensors",
          "body": "Matched fault timestamps to nearby engine sensor rows.",
          "agent_name": "Muninn",
          "agent_tagline": "Recalls what normal looks like"
        },
        {
          "agent": "muninn",
          "node": "recommendation",
          "kind": "deterministic",
          "summary": "Ranked what to inspect next from SQL facts only.",
          "title": "State next checks",
          "body": "Ranked what to inspect next from SQL facts only.",
          "agent_name": "Muninn",
          "agent_tagline": "Recalls what normal looks like"
        },
        {
          "agent": "corvus",
          "node": "report_writer",
          "kind": "deterministic",
          "summary": "Saved the finding with trace id for audit.",
          "title": "Save finding",
          "body": "Saved the finding with trace id for audit.",
          "agent_name": "Corvus",
          "agent_tagline": "Writes the report"
        }
      ],
      "agentTraceId": "agent-7874ca2d26ea45c5b1162fd2eac30ddf",
      "dtcSummary": "No DTC rows were logged for this session."
    }
  },
  "sessions": [
    {
      "session_id": 3,
      "vehicle": "Seat Leon",
      "source": "public",
      "notes": "KIT/RADAR Automotive OBD-II Dataset real OBD-II entry; source_file=2018-03-26_Seat_Leon_S_RT_Stau.csv; drive_label=Traffic jam log; license=CC BY 4.0.",
      "source_file": "2018-03-26_Seat_Leon_S_RT_Stau.csv",
      "drive_label": "Traffic jam log",
      "health_score": "100.0",
      "health_score_width": "100.0%",
      "telemetry_samples": "240",
      "dtc_count": "0",
      "pct_out_of_range": "0.0",
      "baseline_width": "0.0%"
    },
    {
      "session_id": 4,
      "vehicle": "VED ICE 6.0L V8",
      "source": "public",
      "notes": "Vehicle Energy Dataset (VED) real OBD-II entry; source_file=VED_171101_week.csv; trip_ref=VehId=108; Trip=784; drive_label=Ann Arbor week log; license=Apache-2.0.",
      "source_file": "VED_171101_week.csv",
      "drive_label": "Ann Arbor week log",
      "health_score": "96.2",
      "health_score_width": "96.2%",
      "telemetry_samples": "240",
      "dtc_count": "0",
      "pct_out_of_range": "0.0",
      "baseline_width": "0.0%"
    },
    {
      "session_id": 5,
      "vehicle": "VED Car 1.5L",
      "source": "public",
      "notes": "Vehicle Energy Dataset (VED) real OBD-II entry; source_file=VED_171101_week.csv; trip_ref=VehId=8; Trip=708; drive_label=Ann Arbor week log; license=Apache-2.0.",
      "source_file": "VED_171101_week.csv",
      "drive_label": "Ann Arbor week log",
      "health_score": "95.0",
      "health_score_width": "95.0%",
      "telemetry_samples": "240",
      "dtc_count": "0",
      "pct_out_of_range": "0.0",
      "baseline_width": "0.0%"
    }
  ],
  "trend": [
    {
      "ts": "2017-11-02T13:51:53.106Z",
      "maf_gps": "6.70",
      "maf_30s": "6.70",
      "height_pct": "43.4%"
    },
    {
      "ts": "2017-11-02T13:51:58.906Z",
      "maf_gps": "15.60",
      "maf_30s": "12.36",
      "height_pct": "68.2%"
    },
    {
      "ts": "2017-11-02T13:52:06.606Z",
      "maf_gps": "4.48",
      "maf_30s": "9.86",
      "height_pct": "57.3%"
    },
    {
      "ts": "2017-11-02T13:52:12.806Z",
      "maf_gps": "9.54",
      "maf_30s": "8.63",
      "height_pct": "51.9%"
    },
    {
      "ts": "2017-11-02T13:52:19.306Z",
      "maf_gps": "15.69",
      "maf_30s": "9.55",
      "height_pct": "55.9%"
    },
    {
      "ts": "2017-11-02T13:52:26.706Z",
      "maf_gps": "6.91",
      "maf_30s": "9.80",
      "height_pct": "57.0%"
    },
    {
      "ts": "2017-11-02T13:52:36.206Z",
      "maf_gps": "18.97",
      "maf_30s": "12.01",
      "height_pct": "66.7%"
    },
    {
      "ts": "2017-11-02T13:52:43.506Z",
      "maf_gps": "6.15",
      "maf_30s": "11.14",
      "height_pct": "62.9%"
    },
    {
      "ts": "2017-11-02T13:52:53.806Z",
      "maf_gps": "2.93",
      "maf_30s": "9.18",
      "height_pct": "54.3%"
    },
    {
      "ts": "2017-11-02T13:53:03.306Z",
      "maf_gps": "2.96",
      "maf_30s": "6.52",
      "height_pct": "42.6%"
    },
    {
      "ts": "2017-11-02T13:53:13.806Z",
      "maf_gps": "3.55",
      "maf_30s": "3.48",
      "height_pct": "29.3%"
    },
    {
      "ts": "2017-11-02T13:53:19.106Z",
      "maf_gps": "3.52",
      "maf_30s": "3.31",
      "height_pct": "28.5%"
    },
    {
      "ts": "2017-11-02T13:53:24.806Z",
      "maf_gps": "16.65",
      "maf_30s": "3.90",
      "height_pct": "31.1%"
    },
    {
      "ts": "2017-11-02T13:53:30.706Z",
      "maf_gps": "21.33",
      "maf_30s": "8.19",
      "height_pct": "49.9%"
    },
    {
      "ts": "2017-11-02T13:53:37.906Z",
      "maf_gps": "22.01",
      "maf_30s": "12.26",
      "height_pct": "67.8%"
    },
    {
      "ts": "2017-11-02T13:53:48.606Z",
      "maf_gps": "3.64",
      "maf_30s": "15.31",
      "height_pct": "81.2%"
    },
    {
      "ts": "2017-11-02T13:53:59.006Z",
      "maf_gps": "2.93",
      "maf_30s": "11.13",
      "height_pct": "62.8%"
    },
    {
      "ts": "2017-11-02T13:54:09.406Z",
      "maf_gps": "21.90",
      "maf_30s": "11.17",
      "height_pct": "63.0%"
    },
    {
      "ts": "2017-11-02T13:54:19.206Z",
      "maf_gps": "23.93",
      "maf_30s": "14.85",
      "height_pct": "79.2%"
    },
    {
      "ts": "2017-11-02T13:54:25.706Z",
      "maf_gps": "5.69",
      "maf_30s": "15.95",
      "height_pct": "84.0%"
    },
    {
      "ts": "2017-11-02T13:54:34.106Z",
      "maf_gps": "3.58",
      "maf_30s": "12.95",
      "height_pct": "70.8%"
    },
    {
      "ts": "2017-11-02T13:54:43.406Z",
      "maf_gps": "3.67",
      "maf_30s": "5.73",
      "height_pct": "39.1%"
    },
    {
      "ts": "2017-11-02T13:54:50.706Z",
      "maf_gps": "2.58",
      "maf_30s": "4.14",
      "height_pct": "32.2%"
    },
    {
      "ts": "2017-11-02T13:54:58.006Z",
      "maf_gps": "23.54",
      "maf_30s": "5.46",
      "height_pct": "38.0%"
    },
    {
      "ts": "2017-11-02T13:55:03.506Z",
      "maf_gps": "23.80",
      "maf_30s": "11.88",
      "height_pct": "66.1%"
    }
  ],
  "dtcEvidence": [
    {
      "code": "none logged",
      "status": "none",
      "description": "No diagnostic trouble code was logged in this real public entry.",
      "fault_ts": "",
      "ts": "",
      "rpm": "n/a",
      "engine_load_pct": "n/a",
      "coolant_temp_c": "n/a"
    }
  ],
  "agentTrace": [
    {
      "agent": "corvus",
      "node": "agent_trace",
      "kind": "deterministic",
      "summary": "Trace created before analysis output.",
      "title": "Open trace",
      "body": "Trace created before analysis output.",
      "agent_name": "Corvus",
      "agent_tagline": "Writes the report"
    },
    {
      "agent": "huginn",
      "node": "ingest_normalizer",
      "kind": "deterministic",
      "summary": "Loaded the logged drive from the database.",
      "title": "Load the drive",
      "body": "Loaded the logged drive from the database.",
      "agent_name": "Huginn",
      "agent_tagline": "Reads this drive"
    },
    {
      "agent": "huginn",
      "node": "sql_deviation",
      "kind": "deterministic",
      "summary": "Ran SQL health score, baseline drift, trim trend, and fault-window queries.",
      "title": "Run SQL checks",
      "body": "Ran SQL health score, baseline drift, trim trend, and fault-window queries.",
      "agent_name": "Huginn",
      "agent_tagline": "Reads this drive"
    },
    {
      "agent": "huginn",
      "node": "dtc_interpreter",
      "kind": "deterministic",
      "summary": "Listed diagnostic trouble codes logged on this drive.",
      "title": "Read fault codes",
      "body": "Listed diagnostic trouble codes logged on this drive.",
      "agent_name": "Huginn",
      "agent_tagline": "Reads this drive"
    },
    {
      "agent": "muninn",
      "node": "baseline_recall",
      "kind": "deterministic",
      "summary": "Loaded stored healthy ranges for this vehicle.",
      "title": "Load healthy ranges",
      "body": "Loaded stored healthy ranges for this vehicle.",
      "agent_name": "Muninn",
      "agent_tagline": "Recalls what normal looks like"
    },
    {
      "agent": "muninn",
      "node": "correlation",
      "kind": "deterministic",
      "summary": "Matched fault timestamps to nearby engine sensor rows.",
      "title": "Match faults to sensors",
      "body": "Matched fault timestamps to nearby engine sensor rows.",
      "agent_name": "Muninn",
      "agent_tagline": "Recalls what normal looks like"
    },
    {
      "agent": "muninn",
      "node": "recommendation",
      "kind": "deterministic",
      "summary": "Ranked what to inspect next from SQL facts only.",
      "title": "State next checks",
      "body": "Ranked what to inspect next from SQL facts only.",
      "agent_name": "Muninn",
      "agent_tagline": "Recalls what normal looks like"
    },
    {
      "agent": "corvus",
      "node": "report_writer",
      "kind": "deterministic",
      "summary": "Saved the finding with trace id for audit.",
      "title": "Save finding",
      "body": "Saved the finding with trace id for audit.",
      "agent_name": "Corvus",
      "agent_tagline": "Writes the report"
    }
  ],
  "agentTraceId": "agent-7874ca2d26ea45c5b1162fd2eac30ddf",
  "disclaimer": "Directional diagnostic guidance based on logged data - not a substitute for inspection by a certified technician.",
  "healthGuide": {
    "title": "Drive health score",
    "body": "Composite SQL score for the selected session."
  },
  "trendGuide": {
    "body": "Grams of air per second (mass air flow). Bars show a rolling SQL average over the logged drive."
  },
  "faultGuide": {
    "title": "Fault codes",
    "body": "OBD-II trouble codes logged during the drive. None logged means no code was stored in this public file."
  },
  "dataSource": {
    "summary": "Three real OBD-II vehicles from public archives.",
    "sources": [
      {
        "name": "KIT/RADAR Automotive OBD-II Dataset",
        "license": "CC BY 4.0",
        "licenseUrl": "https://creativecommons.org/licenses/by/4.0/deed.en",
        "url": "https://doi.org/10.35097/1130"
      },
      {
        "name": "Vehicle Energy Dataset (VED)",
        "license": "Apache-2.0",
        "licenseUrl": "https://www.apache.org/licenses/LICENSE-2.0",
        "url": "https://github.com/gsoh/VED"
      }
    ],
    "entries": [
      "2018-03-26_Seat_Leon_S_RT_Stau.csv",
      "VED_171101_week.csv",
      "VED_171101_week.csv"
    ],
    "note": "Each row below is one real public OBD-II log. KIT files are Seat Leon drives. VED files are de-identified U.S. vehicles.",
    "records": [
      {
        "vehicle": "Seat Leon",
        "drive_label": "Traffic jam log",
        "source_file": "2018-03-26_Seat_Leon_S_RT_Stau.csv",
        "license": "e=CC BY 4.",
        "dataset_name": "KIT/RADAR Automotive OBD-II Dataset"
      },
      {
        "vehicle": "VED ICE 6.0L V8",
        "drive_label": "Ann Arbor week log",
        "source_file": "VED_171101_week.csv",
        "license": "e=Apache-2.",
        "dataset_name": "Vehicle Energy Dataset (VED)"
      },
      {
        "vehicle": "VED Car 1.5L",
        "drive_label": "Ann Arbor week log",
        "source_file": "VED_171101_week.csv",
        "license": "e=Apache-2.",
        "dataset_name": "Vehicle Energy Dataset (VED)"
      }
    ]
  },
  "inspiration": {
    "label": "F-Type P340 / Mustang GT 5.0",
    "image": "inspiration/f-type-mustang.jpg"
  }
}
